jupyterlite_sphinx/__init__.py
jupyterlite_sphinx/_try_examples.py
jupyterlite_sphinx/jupyterlite_sphinx.css
jupyterlite_sphinx/jupyterlite_sphinx.js
jupyterlite_sphinx/jupyterlite_sphinx.py
jupyterlite_sphinx-0.22.0.dist-info/METADATA
jupyterlite_sphinx-0.22.0.dist-info/WHEEL
jupyterlite_sphinx-0.22.0.dist-info/licenses/LICENSE
jupyterlite_sphinx-0.22.0.dist-info/RECORD
