Metadata-Version: 2.4
Name: jupyterlite-sphinx
Version: 0.22.0
Summary: Sphinx extension for deploying JupyterLite
Author: JupyterLite Contributors
License: BSD 3-Clause License
License-File: LICENSE
Requires-Python: >=3.9
Requires-Dist: docutils
Requires-Dist: jupyter-server
Requires-Dist: jupyterlab-server
Requires-Dist: jupyterlite-core<0.8,>=0.2
Requires-Dist: jupytext
Requires-Dist: nbformat
Requires-Dist: sphinx>=4
Provides-Extra: dev
Requires-Dist: hatch; extra == 'dev'
Provides-Extra: docs
Requires-Dist: jupyterlite-xeus<4,>=0.1.8; extra == 'docs'
Requires-Dist: myst-parser; extra == 'docs'
Requires-Dist: pydata-sphinx-theme; extra == 'docs'
